Decoder Based RAM Controller/RAM_8x8.v

module decoder3to8 (
    input [2:0] addr,
    output reg [7:0] dec_out
);
    always @(*) begin
        dec_out = 8'b0;
        dec_out[addr] = 1'b1;  
    end
endmodule
module ram8x8_controller (
    input clk,
    input we,             
    input [2:0] addr,      
    input [7:0] din,       
    output reg [7:0] dout  
);
    reg [7:0] ram [7:0];   
    wire [7:0] select;
   
    decoder3to8 dec(.addr(addr), .dec_out(select));
    integer i;
    always @(posedge clk) begin
        if (we) begin
            
            for (i = 0; i < 8; i = i + 1) begin
                if (select[i])
                    ram[i] <= din;
            end
        end
        
        dout <= ram[addr];
    end
endmodule

Decoder Based RAM Controller/RAM_8x8_tb.v

`include "RAM_8x8.v"

module tb_ram8x8_controller;
    reg clk;
    reg we;
    reg [2:0] addr;
    reg [7:0] din;
    wire [7:0] dout;
    ram8x8_controller UUT (
        .clk(clk),
        .we(we),
        .addr(addr),
        .din(din),
        .dout(dout)
    );
    // Clock generation: 10ns period
    initial begin
        clk = 0;
        forever #5 clk = ~clk;
    end
    initial begin
        
        $dumpfile("RAM_8x8.vcd");    
        $dumpvars(0, tb_ram8x8_controller);  

        we = 0; addr = 3'b000; din = 8'h00;
        
        #10 we = 1; addr = 3'b000; din = 8'hAA; // Write 0xAA to address 0
        #10 addr = 3'b001; din = 8'h55;         // Write 0x55 to address 1
        #10 addr = 3'b010; din = 8'hFF;         // Write 0xFF to address 2
        #10 we = 0;
        
        #10 addr = 3'b000; 
        #20 addr = 3'b001; 
        #20 addr = 3'b010;
        #20;
        $finish; 
    end
endmodule

Decoder Based RAM Controller/RAM_8x8.vcd
$date
	Fri Aug 28 16:58:41 2026
$end
$version
	Icarus Verilog
$end
$timescale
	1s
$end
$scope module tb_ram8x8_controller $end
$var wire 8 ! dout [7:0] $end
$var reg 3 " addr [2:0] $end
$var reg 1 # clk $end
$var reg 8 $ din [7:0] $end
$var reg 1 % we $end
$scope module UUT $end
$var wire 3 & addr [2:0] $end
$var wire 1 # clk $end
$var wire 8 ' din [7:0] $end
$var wire 1 % we $end
$var wire 8 ( select [7:0] $end
$var reg 8 ) dout [7:0] $end
$var integer 32 * i [31:0] $end
$scope module dec $end
$var wire 3 + addr [2:0] $end
$var reg 8 , dec_out [7:0] $end
$upscope $end
$upscope $end
$upscope $end
$enddefinitions $end
$comment Show the parameter values. $end
$dumpall
$end
#0
$dumpvars
b1 ,
b0 +
bx *
bx )
b1 (
b0 '
b0 &
0%
b0 $
0#
b0 "
bx !
$end
#5
1#
#10
0#
b10101010 $
b10101010 '
1%
#15
b1000 *
1#
#20
b10 (
b10 ,
0#
b1010101 $
b1010101 '
b1 "
b1 &
b1 +
#25
b1000 *
1#
#30
b100 (
b100 ,
0#
b11111111 $
b11111111 '
b10 "
b10 &
b10 +
#35
b1000 *
1#
#40
0#
0%
#45
b11111111 !
b11111111 )
1#
#50
b1 (
b1 ,
0#
b0 "
b0 &
b0 +
#55
b10101010 !
b10101010 )
1#
#60
0#
#65
1#
#70
b10 (
b10 ,
0#
b1 "
b1 &
b1 +
#75
b1010101 !
b1010101 )
1#
#80
0#
#85
1#
#90
b100 (
b100 ,
0#
b10 "
b10 &
b10 +
#95
b11111111 !
b11111111 )
1#
