Hamming Code Generator and Detector/hamming_code_reciever.v
module hamming_code_reciever(
    input clk,
    input rst,
    input [11:1]recieved,
    output reg [6:0] data_out
);

    reg [3:0]parity;
    reg [11:1]c_recieved;                      //Look for a better case where we dont need this register cuz its inefficient

    always@(posedge clk or posedge rst) begin

        if(rst)   begin
            data_out[6:0]=7'bxxxxxxx; 
        end
        
        else      begin
            parity[3]= recieved[11]^recieved[10]^recieved[9]^recieved[8];
            parity[2]= recieved[7]^recieved[6]^recieved[5]^recieved[4];
            parity[1]= recieved[11]^recieved[10]^recieved[7]^recieved[6]^recieved[3]^recieved[2];
            parity[0]= recieved[11]^recieved[9]^recieved[7]^recieved[5]^recieved[3]^recieved[1];

            if(parity==4'b0000)    begin
                data_out[6:0]={recieved[11],recieved[10],recieved[9],recieved[7],recieved[6],recieved[5],recieved[3]};
            end

            else     begin
                c_recieved=recieved;
                c_recieved[parity]=~recieved[parity];
                data_out[6:0]={c_recieved[11],c_recieved[10],c_recieved[9],c_recieved[7],c_recieved[6],c_recieved[5],c_recieved[3]};
            end

        end

    end
endmodule

Hamming Code Generator and Detector/hamming_code_sender.v
module hamming_code_sender(
    input clk,
    input rst,
    input [6:0]data_in,
    output reg [11:1] send
);

    always@(posedge clk or posedge rst) begin          

        if(rst)   begin
            send[11:1]=11'bxxxxxxxxxxx;
        end
                                                //Note: Even parity is considered
        else      begin
            {send[11],send[10],send[9],send[7],send[6],send[5],send[3]}= data_in[6:0];
            send[8]=send[11]^send[10]^send[9];
            send[4]=send[5]^send[6]^send[7];
            send[2]=send[11]^send[10]^send[7]^send[6]^send[3];
            send[1]=send[11]^send[9]^send[7]^send[5]^send[3];
        end

    end

endmodule

Hamming Code Generator and Detector/hamming_code_tb.v
`timescale 1ns/1ns

`include "hamming_code_sender.v"
`include "hamming_code_reciever.v"

module hamming_code_tb;
    reg clk;
    reg rst;
    reg [6:0]data_in;
    wire [11:1]send;             //Note: It is wire cuz every output from every module(verilog file) must be of wire and not reg type
    reg [11:1]channel;           
    reg [11:1]recieved;
    wire[6:0]data_out;

    hamming_code_sender sut(
        .clk(clk),
        .rst(rst),
        .data_in(data_in),
        .send(send)
    );

    hamming_code_reciever rut(
        .clk(clk),
        .rst(rst),
        .data_out(data_out),
        .recieved(recieved)
    );

    initial
        begin
            {clk,rst,data_in}=0;   
        end

    always #5 clk=~clk;

    initial                            //Using GTKWave
        begin
            $dumpfile("hamming_code.vcd");
            $dumpvars(0,hamming_code_tb);
            #100;
            $finish;
        end

    initial
        begin
            data_in =$random;         //Random 7 bit binary number
            #10;
            channel=send;
            #10;
            recieved=channel^ 11'b00000100000;

            #30;

            data_in =$random;         //Random 7 bit binary number
            #10;
            channel=send;
            #10;
            recieved=channel;
        end

endmodule

Hamming Code Generator and Detector/hamming_code.vcd
$date
	Wed Jul 01 00:57:04 2026
$end
$version
	Icarus Verilog
$end
$timescale
	1ns
$end
$scope module hamming_code_tb $end
$var wire 11 ! send [11:1] $end
$var wire 7 " data_out [6:0] $end
$var reg 11 # channel [11:1] $end
$var reg 1 $ clk $end
$var reg 7 % data_in [6:0] $end
$var reg 11 & recieved [11:1] $end
$var reg 1 ' rst $end
$scope module rut $end
$var wire 1 $ clk $end
$var wire 11 ( recieved [11:1] $end
$var wire 1 ' rst $end
$var reg 11 ) c_recieved [11:1] $end
$var reg 7 * data_out [6:0] $end
$var reg 4 + parity [3:0] $end
$upscope $end
$scope module sut $end
$var wire 1 $ clk $end
$var wire 7 , data_in [6:0] $end
$var wire 1 ' rst $end
$var reg 11 - send [11:1] $end
$upscope $end
$upscope $end
$enddefinitions $end
$comment Show the parameter values. $end
$dumpall
$end
#0
$dumpvars
bx -
b100100 ,
bx +
bx *
bx )
bx (
0'
bx &
b100100 %
0$
bx #
bx "
bx !
$end
#5
b1010101000 !
b1010101000 -
1$
#10
0$
b1010101000 #
#15
1$
#20
0$
b1010001000 &
b1010001000 (
#25
b100100 "
b100100 *
b1010101000 )
b110 +
1$
#30
0$
#35
b1010101000 )
1$
#40
0$
#45
b1010101000 )
1$
#50
0$
b1 %
b1 ,
#55
b1010101000 )
b111 !
b111 -
1$
#60
0$
b111 #
#65
b1010101000 )
1$
#70
0$
b111 &
b111 (
#75
b1 "
b1 *
b0 +
1$
