Elevator Controller/Elevator_Controller.v
module elevator_controller(
    input clk,
    input rst,
    input [3:0]floor_req,
    input emergency_stop,                      //Synchronous emergency stop
    output reg move_u,
    output reg move_d,
    output reg motor_stop,
    output reg [1:0]current_floor
);

parameter idle=2'b00,move_up=2'b01,move_down=2'b10,emergency=2'b11;

reg[1:0]current_state,next_state;

reg[1:0]target_floor;

//priority logic                               //floor_req[3:0]--->target_floor[1:0] using decoder logic
always@(*)begin
    target_floor=current_floor;                //Two buttons at same time suppose 1 & 3,then 1 is gonna have priority 
    if(floor_req[0])
        target_floor=2'd0;
    else if(floor_req[1])
        target_floor=2'd1;
    else if(floor_req[2])
        target_floor=2'd2;
    else if(floor_req[3])
        target_floor=2'd3;
end

//present state logic
always@(posedge clk)begin
    if(rst)
        current_state<=idle;
    else
        current_state<=next_state;
end

//floor tracking logic
always @(posedge clk) begin
    if (rst)
        current_floor <= 2'd0;
    else begin
        if (current_state == move_up && current_floor < 2'd3)
            current_floor <= current_floor + 1'b1;
        else if (current_state == move_down && current_floor > 2'd0)
            current_floor <= current_floor - 1'b1;
    end
end

//next state logic
always@(*)begin 
    next_state=current_state;

    if(emergency_stop)
        next_state=emergency;
    else begin

        case(current_state)
            idle:
                if(target_floor>current_floor)
                    next_state=move_up;
                else if(target_floor<current_floor)
                    next_state=move_down;

            move_up:
                if(target_floor == current_floor)
                    next_state = idle;
                else if(target_floor < current_floor)
                    next_state = move_down;
                else
                    next_state = move_up;

            move_down:
                if(target_floor == current_floor)
                    next_state = idle;
                else if(target_floor > current_floor)
                    next_state = move_up;
                else
                    next_state = move_down;

            emergency:
                if(emergency_stop)
                    next_state=emergency;
                else
                    next_state=idle;
        endcase   
    end
end

//output logic
always@(*)begin 
    move_u=1'b0;
    move_d=1'b0;
    motor_stop=1'b0;

    case(current_state)
        move_up:
            move_u=1'b1;
        move_down:
            move_d=1'b1;
        emergency:
            motor_stop=1'b1;
        idle:
            motor_stop=1'b1;
    endcase
end
endmodule

Elevator Controller/Elevator_Controller_tb.v
`timescale 1ns/1ns

`include "Elevator_Controller.v"

module elevator_controller_tb;

reg clk;
reg rst;
reg[3:0]floor_req;
reg emergency_stop;

wire move_u;
wire move_d;
wire motor_stop;
wire[1:0]current_floor;

elevator_controller dut(clk,rst,floor_req,emergency_stop,move_u,move_d,motor_stop,current_floor);

always#5 clk =~clk;

initial                            //Using GTKWave
        begin
            $dumpfile("Elevator_Controller.vcd");
            $dumpvars(0,elevator_controller_tb);
            #200;
            $finish;
        end

//Test sequence
initial begin
    clk=0;
    rst=1;
    floor_req=4'b0000;
    emergency_stop=0;

    #20 rst=0;

    #10 floor_req=4'b0100;

    #20 floor_req=4'b0010;

    #20 floor_req=4'b1000;

    #20 floor_req=4'b1010; //Two buttons at same time

    #20 emergency_stop=1;

    #10 emergency_stop=0;

    #20 floor_req=4'b0001;

end
endmodule

Elevator Controller/Elevator_Controller.vcd
$date
	Wed Aug 19 02:01:23 2026
$end
$version
	Icarus Verilog
$end
$timescale
	1ns
$end
$scope module elevator_controller_tb $end
$var wire 1 ! move_u $end
$var wire 1 " move_d $end
$var wire 1 # motor_stop $end
$var wire 2 $ current_floor [1:0] $end
$var reg 1 % clk $end
$var reg 1 & emergency_stop $end
$var reg 4 ' floor_req [3:0] $end
$var reg 1 ( rst $end
$scope module dut $end
$var wire 1 % clk $end
$var wire 1 & emergency_stop $end
$var wire 4 ) floor_req [3:0] $end
$var wire 1 ( rst $end
$var parameter 2 * emergency $end
$var parameter 2 + idle $end
$var parameter 2 , move_down $end
$var parameter 2 - move_up $end
$var reg 2 . current_floor [1:0] $end
$var reg 2 / current_state [1:0] $end
$var reg 1 # motor_stop $end
$var reg 1 " move_d $end
$var reg 1 ! move_u $end
$var reg 2 0 next_state [1:0] $end
$var reg 2 1 target_floor [1:0] $end
$upscope $end
$upscope $end
$enddefinitions $end
$comment Show the parameter values. $end
$dumpall
b1 -
b10 ,
b0 +
b11 *
$end
#0
$dumpvars
bx 1
bx 0
bx /
bx .
b0 )
1(
b0 '
0&
0%
bx $
x#
x"
x!
$end
#5
1#
0"
0!
b0 0
b0 1
b0 /
b0 $
b0 .
1%
#10
0%
#15
1%
#20
0%
0(
#25
1%
#30
b1 0
b10 1
0%
b100 '
b100 )
#35
1!
0#
b1 /
1%
#40
0%
#45
b10 1
b1 $
b1 .
1%
#50
b0 0
b1 1
0%
b10 '
b10 )
#55
b1 1
1#
0!
b10 0
b10 $
b10 .
b0 /
1%
#60
0%
#65
1"
0#
b10 /
1%
#70
b1 0
b11 1
0%
b1000 '
b1000 )
#75
b11 1
1!
0"
b1 $
b1 .
b1 /
1%
#80
0%
#85
b11 1
b10 $
b10 .
1%
#90
b10 0
b1 1
0%
b1010 '
b1010 )
#95
b1 1
1"
0!
b11 $
b11 .
b10 /
1%
#100
0%
#105
b1 1
b10 $
b10 .
1%
#110
b11 0
0%
1&
#115
1#
0"
b1 $
b1 .
b11 /
1%
#120
b0 0
0%
0&
#125
1#
b0 /
1%
#130
0%
#135
1%
#140
b10 0
b0 1
0%
b1 '
b1 )
#145
1"
0#
b10 /
1%
#150
0%
#155
b0 0
b0 $
b0 .
1%
#160
0%
#165
1#
0"
b0 /
1%
