AXI Lite Slave Interface/AXI_lite_slave.v
module axi_lite_slave (
    input wire aclk,
    input wire aresetn,
    // Write Address Channel
    input wire [31:0] awaddr,
    input wire awvalid,
    output reg awready,
    // Write Data Channel
    input wire [31:0] wdata,
    input wire [3:0] wstrb,
    input wire wvalid,
    output reg wready,
    // Write Response Channel
    output reg [1:0] bresp,
    output reg bvalid,
    input wire bready,
    // Read Address Channel
    input wire [31:0] araddr,
    input wire arvalid,
    output reg arready,
    // Read Data Channel
    output reg [31:0] rdata,
    output reg [1:0] rresp,
    output reg       rvalid,
    input wire       rready
);

reg [31:0] mem [0:255];
reg [7:0]  wr_addr;  // Latched write address
reg [7:0]  rd_addr;  // Latched read address

always @(posedge aclk) begin
    if (!aresetn) begin
        awready <= 0;
        wready  <= 0;
        bvalid  <= 0;
        arready <= 0;
        rvalid  <= 0;
    end else begin
        // Write Address Latching
        if (awvalid && !awready) begin
            awready <= 1;
            wr_addr <= awaddr[7:0];  // Latch write address
        end else begin
            awready <= 0;
        end

        // Write Data and Response
        if (wvalid && awready) begin
            wready <= 1;
            mem[wr_addr] <= wdata;  // Write to latched address
            bresp <= 2'b00;
            bvalid <= 1;
        end
        if (bvalid && bready) begin
            bvalid <= 0;
        end

        // Read Address Latching
        if (arvalid && !arready) begin
            arready <= 1;
            rd_addr <= araddr[7:0];  // Latch read address
        end else begin
            arready <= 0;
        end

        // Read Data
        if (arready) begin
            rdata <= mem[rd_addr];  // Read from latched address
            rresp <= 2'b00;
            rvalid <= 1;
        end
        if (rvalid && rready) begin
            rvalid <= 0;
        end
    end
end
endmodule

AXI Lite Slave Interface/AXI_lite_slave_tb.v
`timescale 1ns/1ps

`include"AXI_lite_slave.v"

module tb_axi_lite;
    reg aclk;
    reg aresetn;
    reg [31:0] awaddr;
    reg awvalid;
    wire awready;
    reg [31:0] wdata;
    reg [3:0] wstrb;
    reg wvalid;
    wire wready;
    wire [1:0] bresp;
    wire bvalid;
    reg bready;
    reg [31:0] araddr;
    reg arvalid;
    wire arready;
    wire [31:0] rdata;
    wire [1:0] rresp;
    wire rvalid;
    reg rready;

    axi_lite_slave uut (
        .aclk(aclk), .aresetn(aresetn),
        .awaddr(awaddr), .awvalid(awvalid), .awready(awready),
        .wdata(wdata), .wstrb(wstrb), .wvalid(wvalid), .wready(wready),
        .bresp(bresp), .bvalid(bvalid), .bready(bready),
        .araddr(araddr), .arvalid(arvalid), .arready(arready),
        .rdata(rdata), .rresp(rresp), .rvalid(rvalid), .rready(rready)
    );

    initial begin
        aclk = 0;
        forever #5 aclk = ~aclk;
    end

    initial begin
        // VCD file generation
        $dumpfile("AXI_lite_slave.vcd");
        $dumpvars(0, tb_axi_lite);

        $display("Starting AXI Lite transactions...");

        araddr = 32'h04;
        awaddr  = 32'h04;
        wdata   = 32'h100;
        aresetn = 0;
        arvalid = 0;
        rready  = 0;
        awvalid = 0;
        wvalid  = 0;
        bready  = 0;

        #10 aresetn = 1;

        // Multiple Write Transactions
        repeat (3) begin
            @(posedge aclk);
            awaddr  = awaddr + 32'h04;
            awvalid = 1;
            wdata   = wdata + 32'h100;
            wstrb   = 4'b1111;
            wvalid = 1;
            bready = 1;

            $display("Write Transaction: Addr = %h, Data = %h", awaddr, wdata);
            @(posedge aclk);
            //  @(posedge aclk);
            awvalid = 0;
            wvalid = 0;
            bready = 0;
            awvalid = 0;
            wvalid = 0;
            bready = 0;
        end

        // Multiple Read Transactions
        repeat (3) begin
            @(posedge aclk);
            araddr = araddr + 32'h04;
            arvalid = 1;
            rready = 1;
            @(posedge aclk);
            @(negedge aclk);
            $display("Read Transaction: Addr = %h, Data = %h", araddr, rdata);

            arvalid = 0;
            rready = 0;
        end

        #50 $finish;
    end
endmodule

AXI Lite Slave Interface/AXI_lite_slave.vcd
$date
	Fri Aug 28 17:34:16 2026
$end
$version
	Icarus Verilog
$end
$timescale
	1ps
$end
$scope module tb_axi_lite $end
$var wire 1 ! wready $end
$var wire 1 " rvalid $end
$var wire 2 # rresp [1:0] $end
$var wire 32 $ rdata [31:0] $end
$var wire 1 % bvalid $end
$var wire 2 & bresp [1:0] $end
$var wire 1 ' awready $end
$var wire 1 ( arready $end
$var reg 1 ) aclk $end
$var reg 32 * araddr [31:0] $end
$var reg 1 + aresetn $end
$var reg 1 , arvalid $end
$var reg 32 - awaddr [31:0] $end
$var reg 1 . awvalid $end
$var reg 1 / bready $end
$var reg 1 0 rready $end
$var reg 32 1 wdata [31:0] $end
$var reg 4 2 wstrb [3:0] $end
$var reg 1 3 wvalid $end
$scope module uut $end
$var wire 1 ) aclk $end
$var wire 32 4 araddr [31:0] $end
$var wire 1 + aresetn $end
$var wire 1 , arvalid $end
$var wire 32 5 awaddr [31:0] $end
$var wire 1 . awvalid $end
$var wire 1 / bready $end
$var wire 1 0 rready $end
$var wire 32 6 wdata [31:0] $end
$var wire 4 7 wstrb [3:0] $end
$var wire 1 3 wvalid $end
$var reg 1 ( arready $end
$var reg 1 ' awready $end
$var reg 2 8 bresp [1:0] $end
$var reg 1 % bvalid $end
$var reg 8 9 rd_addr [7:0] $end
$var reg 32 : rdata [31:0] $end
$var reg 2 ; rresp [1:0] $end
$var reg 1 " rvalid $end
$var reg 8 < wr_addr [7:0] $end
$var reg 1 ! wready $end
$upscope $end
$upscope $end
$enddefinitions $end
$comment Show the parameter values. $end
$dumpall
$end
#0
$dumpvars
bx <
bx ;
bx :
bx 9
bx 8
bx 7
b100000000 6
b100 5
b100 4
03
bx 2
b100000000 1
00
0/
0.
b100 -
0,
0+
b100 *
0)
x(
x'
bx &
x%
bx $
bx #
x"
x!
$end
#5000
0"
0(
0%
0!
0'
1)
#10000
0)
1+
#15000
b1000 <
1'
1/
13
b1111 2
b1111 7
b1000000000 1
b1000000000 6
1.
b1000 -
b1000 5
1)
#20000
0)
#25000
1%
b0 &
b0 8
1!
0'
0/
03
0.
1)
#30000
0)
#35000
0%
b1100 <
1'
1/
13
b1100000000 1
b1100000000 6
1.
b1100 -
b1100 5
1)
#40000
0)
#45000
1%
0'
0/
03
0.
1)
#50000
0)
#55000
0%
b10000 <
1'
1/
13
b10000000000 1
b10000000000 6
1.
b10000 -
b10000 5
1)
#60000
0)
#65000
1%
0'
0/
03
0.
1)
#70000
0)
#75000
b1000 9
1(
10
1,
b1000 *
b1000 4
1)
#80000
0)
#85000
1"
b0 #
b0 ;
b1000000000 $
b1000000000 :
0(
1)
#90000
00
0,
0)
#95000
0"
b1100 9
1(
10
1,
b1100 *
b1100 4
1)
#100000
0)
#105000
1"
b1100000000 $
b1100000000 :
0(
1)
#110000
00
0,
0)
#115000
0"
b10000 9
1(
10
1,
b10000 *
b10000 4
1)
#120000
0)
#125000
1"
b10000000000 $
b10000000000 :
0(
1)
#130000
00
0,
0)
